odoo/addons/free_delivery_untaxed/README.rst
odoo/addons/free_delivery_untaxed/__init__.py
odoo/addons/free_delivery_untaxed/__manifest__.py
odoo/addons/free_delivery_untaxed/i18n/es.po
odoo/addons/free_delivery_untaxed/models/__init__.py
odoo/addons/free_delivery_untaxed/models/delivery_carrier.py
odoo/addons/free_delivery_untaxed/models/sale_order.py
odoo/addons/free_delivery_untaxed/static/description/icon.png
odoo/addons/free_delivery_untaxed/views/delivery_view.xml
odoo_addon_free_delivery_untaxed-15.0.1.0.0.4.dist-info/METADATA
odoo_addon_free_delivery_untaxed-15.0.1.0.0.4.dist-info/WHEEL
odoo_addon_free_delivery_untaxed-15.0.1.0.0.4.dist-info/top_level.txt
odoo_addon_free_delivery_untaxed-15.0.1.0.0.4.dist-info/RECORD
